optimal_psychophysics-0.1.1.dist-info/METADATA
optimal_psychophysics-0.1.1.dist-info/WHEEL
optimal_psychophysics/__init__.py
optimal_psychophysics/optimal_psychophysics.abi3.so
optimal_psychophysics-0.1.1.dist-info/RECORD
