Metadata-Version: 2.3
Name: optimal-psychophysics
Version: 0.1.1
Classifier: Programming Language :: Rust
Classifier: Programming Language :: Python :: Implementation :: CPython
Classifier: Programming Language :: Python :: Implementation :: PyPy
Summary: Python library for optimal psychophysics design and adaptive testing
Author-email: Marc Pabst <mail@marcpabst.com>
License: MPL-2.0
Requires-Python: >=3.7
